hierdiff/__init__.py
hierdiff/association_testing.py
hierdiff/hier_plot.py
hierdiff/modified_scipy_dendrogram.py
hierdiff/tally.py
hierdiff/templates/__init__.py
hierdiff/templates/minimal.html
hierdiff/templates/tree_template.html
hierdiff/tests/__init__.py
hierdiff/tests/data_generator.py
hierdiff/tests/test_assoc.py
hierdiff/tests/test_plot.py
hierdiff/tests/test_tally.py
hierdiff-0.85.dist-info/LICENSE
hierdiff-0.85.dist-info/METADATA
hierdiff-0.85.dist-info/WHEEL
hierdiff-0.85.dist-info/top_level.txt
hierdiff-0.85.dist-info/RECORD
