Metadata-Version: 2.1
Name: hierdiff
Version: 0.85
Summary: Clustering high-dimensional instances (e.g. T cell receptors) and testing whether clusters of instances are differentially abundant in two or more categorical conditions, with interactive tree visualization.
Home-page: https://github.com/agartland/hierdiff
Author: Andrew Fiore-Gartland
Author-email: agartlan@fredhutch.org
Maintainer: Andrew Fiore-Gartland
Maintainer-email: agartlan@fredhutch.org
License: MIT
License-File: LICENSE
Requires-Dist: numpy >=1.18.1
Requires-Dist: pandas >=0.24.2
Requires-Dist: scipy >=1.4.1
Requires-Dist: jinja2 >=2.10.1
Requires-Dist: statsmodels >=0.10
Requires-Dist: fishersapi >=0.1.2
Requires-Dist: joblib >=0.16
